servers/__init__.py
servers/basic_add.py
servers/basic_multi.py
mcp2-0.1.2.dist-info/METADATA
mcp2-0.1.2.dist-info/WHEEL
mcp2-0.1.2.dist-info/entry_points.txt
mcp2-0.1.2.dist-info/top_level.txt
mcp2-0.1.2.dist-info/RECORD
