Metadata-Version: 2.4
Name: mcp2
Version: 0.1.2
Summary: Add your description here
Requires-Python: >=3.12
Requires-Dist: mcp[cli]>=1.13.0
